opal_fetcher_mongodb/__init__.py
opal_fetcher_mongodb/provider.py
opal_fetcher_mongodb_treedom-0.0.1.dist-info/LICENSE
opal_fetcher_mongodb_treedom-0.0.1.dist-info/METADATA
opal_fetcher_mongodb_treedom-0.0.1.dist-info/WHEEL
opal_fetcher_mongodb_treedom-0.0.1.dist-info/top_level.txt
opal_fetcher_mongodb_treedom-0.0.1.dist-info/RECORD
