Metadata-Version: 2.1
Name: opal-fetcher-mongodb-treedom
Version: 0.0.1
Summary: An OPAL fetch provider to bring authorization state from MongoDB.
Author-email: Ionut Andrei Oanca <ia.oanca@treedom.net>
License: Apache-2.0
Project-URL: Source, https://github.com/treedomtrees/opal-fetcher-mongodb
Project-URL: Bug Tracker, https://github.com/treedomtrees/opal-fetcher-mongodb/issues
Keywords: Open Policy Agent,OPA,OPAL,Open Policy Administration Layer,MongoDB,Permit.io
Classifier: Operating System :: OS Independent
Classifier: License :: OSI Approved :: Apache Software License
Classifier: Topic :: Software Development :: Libraries :: Python Modules
Classifier: Programming Language :: Python
Classifier: Programming Language :: Python :: 3
Classifier: Programming Language :: Python :: 3.7
Classifier: Programming Language :: Python :: 3.8
Classifier: Programming Language :: Python :: 3.9
Requires-Python: >=3.7
License-File: LICENSE
Requires-Dist: opal-common >=0.1.11
Requires-Dist: pymongo
Requires-Dist: motor
Requires-Dist: pydantic
Requires-Dist: tenacity
Requires-Dist: click
